[
  {
    "Capacity": "40",
    "IsAvailable": true,
    "Name": "Sec1",
    "Type": "Ex"
  },
  {
    "Capacity": "40",
    "IsAvailable": true,
    "Name": "Sec2",
    "Type": "Ex"
  },
  {
    "Capacity": "40",
    "IsAvailable": true,
    "Name": "Sec3",
    "Type": "Ex"
  },
  {
    "Capacity": "40",
    "IsAvailable": true,
    "Name": "Sec4",
    "Type": "Ex"
  },
  {
    "Capacity": "40",
    "IsAvailable": true,
    "Name": "Sec5",
    "Type": "Ex"
  },
  {
    "Capacity": "40",
    "IsAvailable": true,
    "Name": "Sec6",
    "Type": "Ex"
  },
  {
    "Capacity": "40",
    "IsAvailable": true,
    "Name": "Sec7",
    "Type": "Ex"
  },
  {
    "Capacity": "40",
    "IsAvailable": true,
    "Name": "Sec8",
    "Type": "Ex"
  },
  {
    "Capacity": "40",
    "IsAvailable": true,
    "Name": "Sec9",
    "Type": "Ex"
  },
  {
    "Capacity": "40",
    "IsAvailable": true,
    "Name": "Sec10",
    "Type": "Ex"
  },
  {
    "Capacity": "40",
    "IsAvailable": true,
    "Name": "Sec11",
    "Type": "Ex"
  },
  {
    "Capacity": "40",
    "IsAvailable": true,
    "Name": "Sec12",
    "Type": "Ex"
  },
  {
    "Capacity": "28",
    "IsAvailable": true,
    "Name": "Lab1",
    "Type": "Lab"
  },
  {
    "Capacity": "28",
    "IsAvailable": true,
    "Name": "Lab2",
    "Type": "Lab"
  },
  {
    "Capacity": "28",
    "IsAvailable": true,
    "Name": "Lab3",
    "Type": "Lab"
  },
  {
    "Capacity": "28",
    "IsAvailable": true,
    "Name": "Lab4",
    "Type": "Lab"
  },
  {
    "Capacity": "28",
    "IsAvailable": true,
    "Name": "Lab5",
    "Type": "Lab"
  },
  {
    "Capacity": "28",
    "IsAvailable": true,
    "Name": "Lab6",
    "Type": "Lab"
  },
  {
    "Capacity": "200",
    "IsAvailable": true,
    "Name": "L1",
    "Type": "L"
  },
  {
    "Capacity": "200",
    "IsAvailable": true,
    "Name": "L2",
    "Type": "L"
  },
  {
    "Capacity": "200",
    "IsAvailable": true,
    "Name": "L3",
    "Type": "L"
  },
  {
    "Capacity": "28",
    "IsAvailable": true,
    "Name": "Sec1/Lab1",
    "Type": "Ex/Lab"
  },
  {
    "Capacity": "28",
    "IsAvailable": true,
    "Name": "Sec1/Lab2",
    "Type": "Ex/Lab"
  },
  {
    "Capacity": "28",
    "IsAvailable": true,
    "Name": "Sec1/Lab3",
    "Type": "Ex/Lab"
  },
  {
    "Capacity": "28",
    "IsAvailable": true,
    "Name": "Sec1/Lab4",
    "Type": "Ex/Lab"
  },
  {
    "Capacity": "28",
    "IsAvailable": true,
    "Name": "Sec1/Lab5",
    "Type": "Ex/Lab"
  },
  {
    "Capacity": "28",
    "IsAvailable": true,
    "Name": "Sec1/Lab6",
    "Type": "Ex/Lab"
  },
  {
    "Capacity": "28",
    "IsAvailable": true,
    "Name": "Sec2/Lab1",
    "Type": "Ex/Lab"
  },
  {
    "Capacity": "28",
    "IsAvailable": true,
    "Name": "Sec2/Lab2",
    "Type": "Ex/Lab"
  },
  {
    "Capacity": "28",
    "IsAvailable": true,
    "Name": "Sec2/Lab3",
    "Type": "Ex/Lab"
  },
  {
    "Capacity": "28",
    "IsAvailable": true,
    "Name": "Sec2/Lab4",
    "Type": "Ex/Lab"
  },
  {
    "Capacity": "28",
    "IsAvailable": true,
    "Name": "Sec2/Lab5",
    "Type": "Ex/Lab"
  },
  {
    "Capacity": "28",
    "IsAvailable": true,
    "Name": "Sec2/Lab6",
    "Type": "Ex/Lab"
  },
  {
    "Capacity": "28",
    "IsAvailable": true,
    "Name": "Sec3/Lab1",
    "Type": "Ex/Lab"
  },
  {
    "Capacity": "28",
    "IsAvailable": true,
    "Name": "Sec3/Lab2",
    "Type": "Ex/Lab"
  },
  {
    "Capacity": "28",
    "IsAvailable": true,
    "Name": "Sec3/Lab3",
    "Type": "Ex/Lab"
  },
  {
    "Capacity": "28",
    "IsAvailable": true,
    "Name": "Sec3/Lab4",
    "Type": "Ex/Lab"
  },
  {
    "Capacity": "28",
    "IsAvailable": true,
    "Name": "Sec3/Lab5",
    "Type": "Ex/Lab"
  },
  {
    "Capacity": "28",
    "IsAvailable": true,
    "Name": "Sec3/Lab6",
    "Type": "Ex/Lab"
  },
  {
    "Capacity": "28",
    "IsAvailable": true,
    "Name": "Sec4/Lab1",
    "Type": "Ex/Lab"
  },
  {
    "Capacity": "28",
    "IsAvailable": true,
    "Name": "Sec4/Lab2",
    "Type": "Ex/Lab"
  },
  {
    "Capacity": "28",
    "IsAvailable": true,
    "Name": "Sec4/Lab3",
    "Type": "Ex/Lab"
  },
  {
    "Capacity": "28",
    "IsAvailable": true,
    "Name": "Sec4/Lab4",
    "Type": "Ex/Lab"
  },
  {
    "Capacity": "28",
    "IsAvailable": true,
    "Name": "Sec4/Lab5",
    "Type": "Ex/Lab"
  },
  {
    "Capacity": "28",
    "IsAvailable": true,
    "Name": "Sec4/Lab6",
    "Type": "Ex/Lab"
  },
  {
    "Capacity": "28",
    "IsAvailable": true,
    "Name": "Sec5/Lab1",
    "Type": "Ex/Lab"
  },
  {
    "Capacity": "28",
    "IsAvailable": true,
    "Name": "Sec5/Lab2",
    "Type": "Ex/Lab"
  },
  {
    "Capacity": "28",
    "IsAvailable": true,
    "Name": "Sec5/Lab3",
    "Type": "Ex/Lab"
  },
  {
    "Capacity": "28",
    "IsAvailable": true,
    "Name": "Sec5/Lab4",
    "Type": "Ex/Lab"
  },
  {
    "Capacity": "28",
    "IsAvailable": true,
    "Name": "Sec5/Lab5",
    "Type": "Ex/Lab"
  },
  {
    "Capacity": "28",
    "IsAvailable": true,
    "Name": "Sec5/Lab6",
    "Type": "Ex/Lab"
  },
  {
    "Capacity": "28",
    "IsAvailable": true,
    "Name": "Sec6/Lab1",
    "Type": "Ex/Lab"
  },
  {
    "Capacity": "28",
    "IsAvailable": true,
    "Name": "Sec6/Lab2",
    "Type": "Ex/Lab"
  },
  {
    "Capacity": "28",
    "IsAvailable": true,
    "Name": "Sec6/Lab3",
    "Type": "Ex/Lab"
  },
  {
    "Capacity": "28",
    "IsAvailable": true,
    "Name": "Sec6/Lab4",
    "Type": "Ex/Lab"
  },
  {
    "Capacity": "28",
    "IsAvailable": true,
    "Name": "Sec6/Lab5",
    "Type": "Ex/Lab"
  },
  {
    "Capacity": "28",
    "IsAvailable": true,
    "Name": "Sec6/Lab6",
    "Type": "Ex/Lab"
  },
  {
    "Capacity": "28",
    "IsAvailable": true,
    "Name": "Sec7/Lab1",
    "Type": "Ex/Lab"
  },
  {
    "Capacity": "28",
    "IsAvailable": true,
    "Name": "Sec7/Lab2",
    "Type": "Ex/Lab"
  },
  {
    "Capacity": "28",
    "IsAvailable": true,
    "Name": "Sec7/Lab3",
    "Type": "Ex/Lab"
  },
  {
    "Capacity": "28",
    "IsAvailable": true,
    "Name": "Sec7/Lab4",
    "Type": "Ex/Lab"
  },
  {
    "Capacity": "28",
    "IsAvailable": true,
    "Name": "Sec7/Lab5",
    "Type": "Ex/Lab"
  },
  {
    "Capacity": "28",
    "IsAvailable": true,
    "Name": "Sec7/Lab6",
    "Type": "Ex/Lab"
  },
  {
    "Capacity": "28",
    "IsAvailable": true,
    "Name": "Sec8/Lab1",
    "Type": "Ex/Lab"
  },
  {
    "Capacity": "28",
    "IsAvailable": true,
    "Name": "Sec8/Lab2",
    "Type": "Ex/Lab"
  },
  {
    "Capacity": "28",
    "IsAvailable": true,
    "Name": "Sec8/Lab3",
    "Type": "Ex/Lab"
  },
  {
    "Capacity": "28",
    "IsAvailable": true,
    "Name": "Sec8/Lab4",
    "Type": "Ex/Lab"
  },
  {
    "Capacity": "28",
    "IsAvailable": true,
    "Name": "Sec8/Lab5",
    "Type": "Ex/Lab"
  },
  {
    "Capacity": "28",
    "IsAvailable": true,
    "Name": "Sec8/Lab6",
    "Type": "Ex/Lab"
  },
  {
    "Capacity": "28",
    "IsAvailable": true,
    "Name": "Sec9/Lab1",
    "Type": "Ex/Lab"
  },
  {
    "Capacity": "28",
    "IsAvailable": true,
    "Name": "Sec9/Lab2",
    "Type": "Ex/Lab"
  },
  {
    "Capacity": "28",
    "IsAvailable": true,
    "Name": "Sec9/Lab3",
    "Type": "Ex/Lab"
  },
  {
    "Capacity": "28",
    "IsAvailable": true,
    "Name": "Sec9/Lab4",
    "Type": "Ex/Lab"
  },
  {
    "Capacity": "28",
    "IsAvailable": true,
    "Name": "Sec9/Lab5",
    "Type": "Ex/Lab"
  },
  {
    "Capacity": "28",
    "IsAvailable": true,
    "Name": "Sec9/Lab6",
    "Type": "Ex/Lab"
  },
  {
    "Capacity": "28",
    "IsAvailable": true,
    "Name": "Sec10/Lab1",
    "Type": "Ex/Lab"
  },
  {
    "Capacity": "28",
    "IsAvailable": true,
    "Name": "Sec10/Lab2",
    "Type": "Ex/Lab"
  },
  {
    "Capacity": "28",
    "IsAvailable": true,
    "Name": "Sec10/Lab3",
    "Type": "Ex/Lab"
  },
  {
    "Capacity": "28",
    "IsAvailable": true,
    "Name": "Sec10/Lab4",
    "Type": "Ex/Lab"
  },
  {
    "Capacity": "28",
    "IsAvailable": true,
    "Name": "Sec10/Lab5",
    "Type": "Ex/Lab"
  },
  {
    "Capacity": "28",
    "IsAvailable": true,
    "Name": "Sec10/Lab6",
    "Type": "Ex/Lab"
  },
  {
    "Capacity": "28",
    "IsAvailable": true,
    "Name": "Sec11/Lab1",
    "Type": "Ex/Lab"
  },
  {
    "Capacity": "28",
    "IsAvailable": true,
    "Name": "Sec11/Lab2",
    "Type": "Ex/Lab"
  },
  {
    "Capacity": "28",
    "IsAvailable": true,
    "Name": "Sec11/Lab3",
    "Type": "Ex/Lab"
  },
  {
    "Capacity": "28",
    "IsAvailable": true,
    "Name": "Sec11/Lab4",
    "Type": "Ex/Lab"
  },
  {
    "Capacity": "28",
    "IsAvailable": true,
    "Name": "Sec11/Lab5",
    "Type": "Ex/Lab"
  },
  {
    "Capacity": "28",
    "IsAvailable": true,
    "Name": "Sec11/Lab6",
    "Type": "Ex/Lab"
  },
  {
    "Capacity": "28",
    "IsAvailable": true,
    "Name": "Sec12/Lab1",
    "Type": "Ex/Lab"
  },
  {
    "Capacity": "28",
    "IsAvailable": true,
    "Name": "Sec12/Lab2",
    "Type": "Ex/Lab"
  },
  {
    "Capacity": "28",
    "IsAvailable": true,
    "Name": "Sec12/Lab3",
    "Type": "Ex/Lab"
  },
  {
    "Capacity": "28",
    "IsAvailable": true,
    "Name": "Sec12/Lab4",
    "Type": "Ex/Lab"
  },
  {
    "Capacity": "28",
    "IsAvailable": true,
    "Name": "Sec12/Lab5",
    "Type": "Ex/Lab"
  },
  {
    "Capacity": "28",
    "IsAvailable": true,
    "Name": "Sec12/Lab6",
    "Type": "Ex/Lab"
  },
  {
    "Capacity": "40",
    "IsAvailable": true,
    "Name": "Sec1/Lab1",
    "Type": "Ex/Lab"
  },
  {
    "Capacity": "40",
    "IsAvailable": true,
    "Name": "Sec1/Lab2",
    "Type": "Ex/Lab"
  },
  {
    "Capacity": "40",
    "IsAvailable": true,
    "Name": "Sec1/Lab3",
    "Type": "Ex/Lab"
  },
  {
    "Capacity": "40",
    "IsAvailable": true,
    "Name": "Sec1/Lab4",
    "Type": "Ex/Lab"
  },
  {
    "Capacity": "40",
    "IsAvailable": true,
    "Name": "Sec1/Lab5",
    "Type": "Ex/Lab"
  },
  {
    "Capacity": "40",
    "IsAvailable": true,
    "Name": "Sec1/Lab6",
    "Type": "Ex/Lab"
  },
  {
    "Capacity": "40",
    "IsAvailable": true,
    "Name": "Sec2/Lab1",
    "Type": "Ex/Lab"
  },
  {
    "Capacity": "40",
    "IsAvailable": true,
    "Name": "Sec2/Lab2",
    "Type": "Ex/Lab"
  },
  {
    "Capacity": "40",
    "IsAvailable": true,
    "Name": "Sec2/Lab3",
    "Type": "Ex/Lab"
  },
  {
    "Capacity": "40",
    "IsAvailable": true,
    "Name": "Sec2/Lab4",
    "Type": "Ex/Lab"
  },
  {
    "Capacity": "40",
    "IsAvailable": true,
    "Name": "Sec2/Lab5",
    "Type": "Ex/Lab"
  },
  {
    "Capacity": "40",
    "IsAvailable": true,
    "Name": "Sec2/Lab6",
    "Type": "Ex/Lab"
  },
  {
    "Capacity": "40",
    "IsAvailable": true,
    "Name": "Sec3/Lab1",
    "Type": "Ex/Lab"
  },
  {
    "Capacity": "40",
    "IsAvailable": true,
    "Name": "Sec3/Lab2",
    "Type": "Ex/Lab"
  },
  {
    "Capacity": "40",
    "IsAvailable": true,
    "Name": "Sec3/Lab3",
    "Type": "Ex/Lab"
  },
  {
    "Capacity": "40",
    "IsAvailable": true,
    "Name": "Sec3/Lab4",
    "Type": "Ex/Lab"
  },
  {
    "Capacity": "40",
    "IsAvailable": true,
    "Name": "Sec3/Lab5",
    "Type": "Ex/Lab"
  },
  {
    "Capacity": "40",
    "IsAvailable": true,
    "Name": "Sec3/Lab6",
    "Type": "Ex/Lab"
  },
  {
    "Capacity": "40",
    "IsAvailable": true,
    "Name": "Sec4/Lab1",
    "Type": "Ex/Lab"
  },
  {
    "Capacity": "40",
    "IsAvailable": true,
    "Name": "Sec4/Lab2",
    "Type": "Ex/Lab"
  },
  {
    "Capacity": "40",
    "IsAvailable": true,
    "Name": "Sec4/Lab3",
    "Type": "Ex/Lab"
  },
  {
    "Capacity": "40",
    "IsAvailable": true,
    "Name": "Sec4/Lab4",
    "Type": "Ex/Lab"
  },
  {
    "Capacity": "40",
    "IsAvailable": true,
    "Name": "Sec4/Lab5",
    "Type": "Ex/Lab"
  },
  {
    "Capacity": "40",
    "IsAvailable": true,
    "Name": "Sec4/Lab6",
    "Type": "Ex/Lab"
  },
  {
    "Capacity": "40",
    "IsAvailable": true,
    "Name": "Sec5/Lab1",
    "Type": "Ex/Lab"
  },
  {
    "Capacity": "40",
    "IsAvailable": true,
    "Name": "Sec5/Lab2",
    "Type": "Ex/Lab"
  },
  {
    "Capacity": "40",
    "IsAvailable": true,
    "Name": "Sec5/Lab3",
    "Type": "Ex/Lab"
  },
  {
    "Capacity": "40",
    "IsAvailable": true,
    "Name": "Sec5/Lab4",
    "Type": "Ex/Lab"
  },
  {
    "Capacity": "40",
    "IsAvailable": true,
    "Name": "Sec5/Lab5",
    "Type": "Ex/Lab"
  },
  {
    "Capacity": "40",
    "IsAvailable": true,
    "Name": "Sec5/Lab6",
    "Type": "Ex/Lab"
  },
  {
    "Capacity": "40",
    "IsAvailable": true,
    "Name": "Sec6/Lab1",
    "Type": "Ex/Lab"
  },
  {
    "Capacity": "40",
    "IsAvailable": true,
    "Name": "Sec6/Lab2",
    "Type": "Ex/Lab"
  },
  {
    "Capacity": "40",
    "IsAvailable": true,
    "Name": "Sec6/Lab3",
    "Type": "Ex/Lab"
  },
  {
    "Capacity": "40",
    "IsAvailable": true,
    "Name": "Sec6/Lab4",
    "Type": "Ex/Lab"
  },
  {
    "Capacity": "40",
    "IsAvailable": true,
    "Name": "Sec6/Lab5",
    "Type": "Ex/Lab"
  },
  {
    "Capacity": "40",
    "IsAvailable": true,
    "Name": "Sec6/Lab6",
    "Type": "Ex/Lab"
  },
  {
    "Capacity": "40",
    "IsAvailable": true,
    "Name": "Sec7/Lab1",
    "Type": "Ex/Lab"
  },
  {
    "Capacity": "40",
    "IsAvailable": true,
    "Name": "Sec7/Lab2",
    "Type": "Ex/Lab"
  },
  {
    "Capacity": "40",
    "IsAvailable": true,
    "Name": "Sec7/Lab3",
    "Type": "Ex/Lab"
  },
  {
    "Capacity": "40",
    "IsAvailable": true,
    "Name": "Sec7/Lab4",
    "Type": "Ex/Lab"
  },
  {
    "Capacity": "40",
    "IsAvailable": true,
    "Name": "Sec7/Lab5",
    "Type": "Ex/Lab"
  },
  {
    "Capacity": "40",
    "IsAvailable": true,
    "Name": "Sec7/Lab6",
    "Type": "Ex/Lab"
  },
  {
    "Capacity": "40",
    "IsAvailable": true,
    "Name": "Sec8/Lab1",
    "Type": "Ex/Lab"
  },
  {
    "Capacity": "40",
    "IsAvailable": true,
    "Name": "Sec8/Lab2",
    "Type": "Ex/Lab"
  },
  {
    "Capacity": "40",
    "IsAvailable": true,
    "Name": "Sec8/Lab3",
    "Type": "Ex/Lab"
  },
  {
    "Capacity": "40",
    "IsAvailable": true,
    "Name": "Sec8/Lab4",
    "Type": "Ex/Lab"
  },
  {
    "Capacity": "40",
    "IsAvailable": true,
    "Name": "Sec8/Lab5",
    "Type": "Ex/Lab"
  },
  {
    "Capacity": "40",
    "IsAvailable": true,
    "Name": "Sec8/Lab6",
    "Type": "Ex/Lab"
  },
  {
    "Capacity": "40",
    "IsAvailable": true,
    "Name": "Sec9/Lab1",
    "Type": "Ex/Lab"
  },
  {
    "Capacity": "40",
    "IsAvailable": true,
    "Name": "Sec9/Lab2",
    "Type": "Ex/Lab"
  },
  {
    "Capacity": "40",
    "IsAvailable": true,
    "Name": "Sec9/Lab3",
    "Type": "Ex/Lab"
  },
  {
    "Capacity": "40",
    "IsAvailable": true,
    "Name": "Sec9/Lab4",
    "Type": "Ex/Lab"
  },
  {
    "Capacity": "40",
    "IsAvailable": true,
    "Name": "Sec9/Lab5",
    "Type": "Ex/Lab"
  },
  {
    "Capacity": "40",
    "IsAvailable": true,
    "Name": "Sec9/Lab6",
    "Type": "Ex/Lab"
  },
  {
    "Capacity": "40",
    "IsAvailable": true,
    "Name": "Sec10/Lab1",
    "Type": "Ex/Lab"
  },
  {
    "Capacity": "40",
    "IsAvailable": true,
    "Name": "Sec10/Lab2",
    "Type": "Ex/Lab"
  },
  {
    "Capacity": "40",
    "IsAvailable": true,
    "Name": "Sec10/Lab3",
    "Type": "Ex/Lab"
  },
  {
    "Capacity": "40",
    "IsAvailable": true,
    "Name": "Sec10/Lab4",
    "Type": "Ex/Lab"
  },
  {
    "Capacity": "40",
    "IsAvailable": true,
    "Name": "Sec10/Lab5",
    "Type": "Ex/Lab"
  },
  {
    "Capacity": "40",
    "IsAvailable": true,
    "Name": "Sec10/Lab6",
    "Type": "Ex/Lab"
  },
  {
    "Capacity": "40",
    "IsAvailable": true,
    "Name": "Sec11/Lab1",
    "Type": "Ex/Lab"
  },
  {
    "Capacity": "40",
    "IsAvailable": true,
    "Name": "Sec11/Lab2",
    "Type": "Ex/Lab"
  },
  {
    "Capacity": "40",
    "IsAvailable": true,
    "Name": "Sec11/Lab3",
    "Type": "Ex/Lab"
  },
  {
    "Capacity": "40",
    "IsAvailable": true,
    "Name": "Sec11/Lab4",
    "Type": "Ex/Lab"
  },
  {
    "Capacity": "40",
    "IsAvailable": true,
    "Name": "Sec11/Lab5",
    "Type": "Ex/Lab"
  },
  {
    "Capacity": "40",
    "IsAvailable": true,
    "Name": "Sec11/Lab6",
    "Type": "Ex/Lab"
  },
  {
    "Capacity": "40",
    "IsAvailable": true,
    "Name": "Sec12/Lab1",
    "Type": "Ex/Lab"
  },
  {
    "Capacity": "40",
    "IsAvailable": true,
    "Name": "Sec12/Lab2",
    "Type": "Ex/Lab"
  },
  {
    "Capacity": "40",
    "IsAvailable": true,
    "Name": "Sec12/Lab3",
    "Type": "Ex/Lab"
  },
  {
    "Capacity": "40",
    "IsAvailable": true,
    "Name": "Sec12/Lab4",
    "Type": "Ex/Lab"
  },
  {
    "Capacity": "40",
    "IsAvailable": true,
    "Name": "Sec12/Lab5",
    "Type": "Ex/Lab"
  },
  {
    "Capacity": "40",
    "IsAvailable": true,
    "Name": "Sec12/Lab6",
    "Type": "Ex/Lab"
  },
  {
    "Capacity": "40",
    "IsAvailable": true,
    "Name": "L1/Sec1",
    "Type": "L/Ex"
  },
  {
    "Capacity": "40",
    "IsAvailable": true,
    "Name": "L1/Sec2",
    "Type": "L/Ex"
  },
  {
    "Capacity": "40",
    "IsAvailable": true,
    "Name": "L1/Sec3",
    "Type": "L/Ex"
  },
  {
    "Capacity": "40",
    "IsAvailable": true,
    "Name": "L1/Sec4",
    "Type": "L/Ex"
  },
  {
    "Capacity": "40",
    "IsAvailable": true,
    "Name": "L1/Sec5",
    "Type": "L/Ex"
  },
  {
    "Capacity": "40",
    "IsAvailable": true,
    "Name": "L1/Sec6",
    "Type": "L/Ex"
  },
  {
    "Capacity": "40",
    "IsAvailable": true,
    "Name": "L1/Sec7",
    "Type": "L/Ex"
  },
  {
    "Capacity": "40",
    "IsAvailable": true,
    "Name": "L1/Sec8",
    "Type": "L/Ex"
  },
  {
    "Capacity": "40",
    "IsAvailable": true,
    "Name": "L1/Sec9",
    "Type": "L/Ex"
  },
  {
    "Capacity": "40",
    "IsAvailable": true,
    "Name": "L1/Sec10",
    "Type": "L/Ex"
  },
  {
    "Capacity": "40",
    "IsAvailable": true,
    "Name": "L1/Sec11",
    "Type": "L/Ex"
  },
  {
    "Capacity": "40",
    "IsAvailable": true,
    "Name": "L1/Sec12",
    "Type": "L/Ex"
  },
  {
    "Capacity": "40",
    "IsAvailable": true,
    "Name": "L2/Sec1",
    "Type": "L/Ex"
  },
  {
    "Capacity": "40",
    "IsAvailable": true,
    "Name": "L2/Sec2",
    "Type": "L/Ex"
  },
  {
    "Capacity": "40",
    "IsAvailable": true,
    "Name": "L2/Sec3",
    "Type": "L/Ex"
  },
  {
    "Capacity": "40",
    "IsAvailable": true,
    "Name": "L2/Sec4",
    "Type": "L/Ex"
  },
  {
    "Capacity": "40",
    "IsAvailable": true,
    "Name": "L2/Sec5",
    "Type": "L/Ex"
  },
  {
    "Capacity": "40",
    "IsAvailable": true,
    "Name": "L2/Sec6",
    "Type": "L/Ex"
  },
  {
    "Capacity": "40",
    "IsAvailable": true,
    "Name": "L2/Sec7",
    "Type": "L/Ex"
  },
  {
    "Capacity": "40",
    "IsAvailable": true,
    "Name": "L2/Sec8",
    "Type": "L/Ex"
  },
  {
    "Capacity": "40",
    "IsAvailable": true,
    "Name": "L2/Sec9",
    "Type": "L/Ex"
  },
  {
    "Capacity": "40",
    "IsAvailable": true,
    "Name": "L2/Sec10",
    "Type": "L/Ex"
  },
  {
    "Capacity": "40",
    "IsAvailable": true,
    "Name": "L2/Sec11",
    "Type": "L/Ex"
  },
  {
    "Capacity": "40",
    "IsAvailable": true,
    "Name": "L2/Sec12",
    "Type": "L/Ex"
  },
  {
    "Capacity": "40",
    "IsAvailable": true,
    "Name": "L3/Sec1",
    "Type": "L/Ex"
  },
  {
    "Capacity": "40",
    "IsAvailable": true,
    "Name": "L3/Sec2",
    "Type": "L/Ex"
  },
  {
    "Capacity": "40",
    "IsAvailable": true,
    "Name": "L3/Sec3",
    "Type": "L/Ex"
  },
  {
    "Capacity": "40",
    "IsAvailable": true,
    "Name": "L3/Sec4",
    "Type": "L/Ex"
  },
  {
    "Capacity": "40",
    "IsAvailable": true,
    "Name": "L3/Sec5",
    "Type": "L/Ex"
  },
  {
    "Capacity": "40",
    "IsAvailable": true,
    "Name": "L3/Sec6",
    "Type": "L/Ex"
  },
  {
    "Capacity": "40",
    "IsAvailable": true,
    "Name": "L3/Sec7",
    "Type": "L/Ex"
  },
  {
    "Capacity": "40",
    "IsAvailable": true,
    "Name": "L3/Sec8",
    "Type": "L/Ex"
  },
  {
    "Capacity": "40",
    "IsAvailable": true,
    "Name": "L3/Sec9",
    "Type": "L/Ex"
  },
  {
    "Capacity": "40",
    "IsAvailable": true,
    "Name": "L3/Sec10",
    "Type": "L/Ex"
  },
  {
    "Capacity": "40",
    "IsAvailable": true,
    "Name": "L3/Sec11",
    "Type": "L/Ex"
  },
  {
    "Capacity": "40",
    "IsAvailable": true,
    "Name": "L3/Sec12",
    "Type": "L/Ex"
  },
  {
    "Capacity": "200",
    "IsAvailable": true,
    "Name": "L1/Sec1",
    "Type": "L/Ex"
  },
  {
    "Capacity": "200",
    "IsAvailable": true,
    "Name": "L1/Sec2",
    "Type": "L/Ex"
  },
  {
    "Capacity": "200",
    "IsAvailable": true,
    "Name": "L1/Sec3",
    "Type": "L/Ex"
  },
  {
    "Capacity": "200",
    "IsAvailable": true,
    "Name": "L1/Sec4",
    "Type": "L/Ex"
  },
  {
    "Capacity": "200",
    "IsAvailable": true,
    "Name": "L1/Sec5",
    "Type": "L/Ex"
  },
  {
    "Capacity": "200",
    "IsAvailable": true,
    "Name": "L1/Sec6",
    "Type": "L/Ex"
  },
  {
    "Capacity": "200",
    "IsAvailable": true,
    "Name": "L1/Sec7",
    "Type": "L/Ex"
  },
  {
    "Capacity": "200",
    "IsAvailable": true,
    "Name": "L1/Sec8",
    "Type": "L/Ex"
  },
  {
    "Capacity": "200",
    "IsAvailable": true,
    "Name": "L1/Sec9",
    "Type": "L/Ex"
  },
  {
    "Capacity": "200",
    "IsAvailable": true,
    "Name": "L1/Sec10",
    "Type": "L/Ex"
  },
  {
    "Capacity": "200",
    "IsAvailable": true,
    "Name": "L1/Sec11",
    "Type": "L/Ex"
  },
  {
    "Capacity": "200",
    "IsAvailable": true,
    "Name": "L1/Sec12",
    "Type": "L/Ex"
  },
  {
    "Capacity": "200",
    "IsAvailable": true,
    "Name": "L2/Sec1",
    "Type": "L/Ex"
  },
  {
    "Capacity": "200",
    "IsAvailable": true,
    "Name": "L2/Sec2",
    "Type": "L/Ex"
  },
  {
    "Capacity": "200",
    "IsAvailable": true,
    "Name": "L2/Sec3",
    "Type": "L/Ex"
  },
  {
    "Capacity": "200",
    "IsAvailable": true,
    "Name": "L2/Sec4",
    "Type": "L/Ex"
  },
  {
    "Capacity": "200",
    "IsAvailable": true,
    "Name": "L2/Sec5",
    "Type": "L/Ex"
  },
  {
    "Capacity": "200",
    "IsAvailable": true,
    "Name": "L2/Sec6",
    "Type": "L/Ex"
  },
  {
    "Capacity": "200",
    "IsAvailable": true,
    "Name": "L2/Sec7",
    "Type": "L/Ex"
  },
  {
    "Capacity": "200",
    "IsAvailable": true,
    "Name": "L2/Sec8",
    "Type": "L/Ex"
  },
  {
    "Capacity": "200",
    "IsAvailable": true,
    "Name": "L2/Sec9",
    "Type": "L/Ex"
  },
  {
    "Capacity": "200",
    "IsAvailable": true,
    "Name": "L2/Sec10",
    "Type": "L/Ex"
  },
  {
    "Capacity": "200",
    "IsAvailable": true,
    "Name": "L2/Sec11",
    "Type": "L/Ex"
  },
  {
    "Capacity": "200",
    "IsAvailable": true,
    "Name": "L2/Sec12",
    "Type": "L/Ex"
  },
  {
    "Capacity": "200",
    "IsAvailable": true,
    "Name": "L3/Sec1",
    "Type": "L/Ex"
  },
  {
    "Capacity": "200",
    "IsAvailable": true,
    "Name": "L3/Sec2",
    "Type": "L/Ex"
  },
  {
    "Capacity": "200",
    "IsAvailable": true,
    "Name": "L3/Sec3",
    "Type": "L/Ex"
  },
  {
    "Capacity": "200",
    "IsAvailable": true,
    "Name": "L3/Sec4",
    "Type": "L/Ex"
  },
  {
    "Capacity": "200",
    "IsAvailable": true,
    "Name": "L3/Sec5",
    "Type": "L/Ex"
  },
  {
    "Capacity": "200",
    "IsAvailable": true,
    "Name": "L3/Sec6",
    "Type": "L/Ex"
  },
  {
    "Capacity": "200",
    "IsAvailable": true,
    "Name": "L3/Sec7",
    "Type": "L/Ex"
  },
  {
    "Capacity": "200",
    "IsAvailable": true,
    "Name": "L3/Sec8",
    "Type": "L/Ex"
  },
  {
    "Capacity": "200",
    "IsAvailable": true,
    "Name": "L3/Sec9",
    "Type": "L/Ex"
  },
  {
    "Capacity": "200",
    "IsAvailable": true,
    "Name": "L3/Sec10",
    "Type": "L/Ex"
  },
  {
    "Capacity": "200",
    "IsAvailable": true,
    "Name": "L3/Sec11",
    "Type": "L/Ex"
  },
  {
    "Capacity": "200",
    "IsAvailable": true,
    "Name": "L3/Sec12",
    "Type": "L/Ex"
  }
]